basher/__init__.py
basher/archive_ops.py
basher/basher.py
basher/core.py
basher/file_ops.py
basher/supervisord.py
basher/system_ops.py
basher2-0.1.5.dist-info/METADATA
basher2-0.1.5.dist-info/WHEEL
basher2-0.1.5.dist-info/top_level.txt
basher2-0.1.5.dist-info/RECORD
