Metadata-Version: 2.1
Name: basher2
Version: 0.1.5
Summary: Python utilities that wrap bash commands
Home-page: https://github.com/genaker/basher
Author: Yehor Shytikov
Author-email: egorshitikov@gmail.com
License: UNKNOWN
Platform: UNKNOWN
Classifier: Programming Language :: Python :: 3
Classifier: License :: OSI Approved :: MIT License
Classifier: Operating System :: POSIX :: Linux
Classifier: Topic :: System :: Systems Administration
Classifier: Topic :: Utilities
Requires-Python: >=3.6
